yanc/__init__.py
yanc/__main__.py
metyanc-0.1.4.dist-info/LICENSE
metyanc-0.1.4.dist-info/METADATA
metyanc-0.1.4.dist-info/WHEEL
metyanc-0.1.4.dist-info/entry_points.txt
metyanc-0.1.4.dist-info/top_level.txt
metyanc-0.1.4.dist-info/RECORD
