Metadata-Version: 2.1
Name: metyanc
Version: 0.1.4
Summary: Yet another NetCDF checker
Home-page: https://github.com/metno/yanc
Author: MET Norway
Author-email: thomas.nipen@met.no
License: GPL-3
Keywords: meteorology weather prediction
Classifier: Development Status :: 4 - Beta
Classifier: Intended Audience :: Science/Research
Classifier: Topic :: Scientific/Engineering :: Atmospheric Science
Classifier: Topic :: Scientific/Engineering :: Information Analysis
Classifier: Programming Language :: Python :: 2.7
Classifier: Programming Language :: Python :: 3.5
License-File: LICENSE
Requires-Dist: numpy (>=1.7)
Requires-Dist: netCDF4
Requires-Dist: pyyaml
Provides-Extra: test
Requires-Dist: coverage ; extra == 'test'
Requires-Dist: pep8 ; extra == 'test'
